airflow_kaldea/__init__.py
airflow_kaldea/__version__.py
airflow_kaldea/operators/__init__.py
airflow_kaldea/operators/kaldea_job_operator.py
airflow_kaldea-0.0.2.dist-info/LICENSE
airflow_kaldea-0.0.2.dist-info/METADATA
airflow_kaldea-0.0.2.dist-info/WHEEL
airflow_kaldea-0.0.2.dist-info/top_level.txt
airflow_kaldea-0.0.2.dist-info/RECORD
