Metadata-Version: 2.1
Name: airflow-kaldea
Version: 0.0.2
Summary: Apache Airflow integration for Kaldea
Home-page: https://github.com/cloa-io/airflow-kaldea
Author: Kaldea
Author-email: support@kaldea.com
License-File: LICENSE
Requires-Dist: apache-airflow (>=1.10.3)
